ferp/__init__.py
ferp/__main__.py
ferp/__version__.py
ferp/app.py
ferp/cli.py
ferp/core/__init__.py
ferp/core/app.py
ferp/core/bundle_installer.py
ferp/core/command_provider.py
ferp/core/dependency_manager.py
ferp/core/fs_controller.py
ferp/core/fs_watcher.py
ferp/core/messages.py
ferp/core/path_actions.py
ferp/core/paths.py
ferp/core/protocols.py
ferp/core/script_controller.py
ferp/core/script_protocol.py
ferp/core/script_runner.py
ferp/core/settings.py
ferp/core/settings_store.py
ferp/core/state.py
ferp/core/task_store.py
ferp/core/transcript_logger.py
ferp/domain/__init__.py
ferp/domain/scripts.py
ferp/fscp/host/__init__.py
ferp/fscp/host/host.py
ferp/fscp/host/managed_process.py
ferp/fscp/host/process_registry.py
ferp/fscp/protocol/__init__.py
ferp/fscp/protocol/errors.py
ferp/fscp/protocol/messages.py
ferp/fscp/protocol/state.py
ferp/fscp/protocol/validator.py
ferp/fscp/protocol/schemas/__init__.py
ferp/fscp/protocol/schemas/fscp/__init__.py
ferp/fscp/protocol/schemas/fscp/1.0/cancel.json
ferp/fscp/protocol/schemas/fscp/1.0/definitions.json
ferp/fscp/protocol/schemas/fscp/1.0/discriminator.json
ferp/fscp/protocol/schemas/fscp/1.0/envelope.json
ferp/fscp/protocol/schemas/fscp/1.0/exit.json
ferp/fscp/protocol/schemas/fscp/1.0/init.json
ferp/fscp/protocol/schemas/fscp/1.0/input_response.json
ferp/fscp/protocol/schemas/fscp/1.0/log.json
ferp/fscp/protocol/schemas/fscp/1.0/message.json
ferp/fscp/protocol/schemas/fscp/1.0/progress.json
ferp/fscp/protocol/schemas/fscp/1.0/request_input.json
ferp/fscp/protocol/schemas/fscp/1.0/result.json
ferp/fscp/scripts/__init__.py
ferp/fscp/scripts/sdk.py
ferp/fscp/scripts/runtime/__init__.py
ferp/fscp/scripts/runtime/__main__.py
ferp/fscp/scripts/runtime/errors.py
ferp/fscp/scripts/runtime/io.py
ferp/fscp/scripts/runtime/script.py
ferp/fscp/scripts/runtime/state.py
ferp/fscp/scripts/runtime/worker.py
ferp/fscp/transcript/__init__.py
ferp/fscp/transcript/events.py
ferp/resources/__init__.py
ferp/services/__init__.py
ferp-0.6.10.dist-info/licenses/LICENSE
ferp-0.6.10.dist-info/METADATA
ferp-0.6.10.dist-info/WHEEL
ferp-0.6.10.dist-info/entry_points.txt
ferp-0.6.10.dist-info/top_level.txt
ferp-0.6.10.dist-info/RECORD
