Metadata-Version: 2.4
Name: ferp
Version: 0.6.10
Summary: Terminal-first file navigator and FSCP automation workbench built with Textual.
Author: Brandon Johnson
License: MIT
Project-URL: Homepage, https://github.com/zappbrandigan/ferp
Project-URL: Documentation, https://github.com/zappbrandigan/ferp#readme
Project-URL: Issues, https://github.com/zappbrandigan/ferp/issues
Classifier: Environment :: Console
Classifier: License :: OSI Approved :: MIT License
Classifier: Topic :: System :: Shells
Classifier: Topic :: Utilities
Classifier: Programming Language :: Python :: 3
Classifier: Programming Language :: Python :: 3 :: Only
Classifier: Programming Language :: Python :: 3.13
Requires-Python: >=3.13
License-File: LICENSE
Requires-Dist: jsonschema>=4.21
Requires-Dist: watchdog>=4.0
Requires-Dist: textual>=7.4.0
Requires-Dist: platformdirs>=4.2
Requires-Dist: requests>=2.32
Provides-Extra: dev
Requires-Dist: pypdf>=6.6; extra == "dev"
Requires-Dist: extract-msg>=0.55.0; extra == "dev"
Requires-Dist: openpyxl>=3.1; extra == "dev"
Requires-Dist: xlwings>=0.33; extra == "dev"
Requires-Dist: googletrans==4.0.2; extra == "dev"
Requires-Dist: Unidecode>=1.3.8; extra == "dev"
Requires-Dist: pywin32>=306; platform_system == "Windows" and extra == "dev"
Requires-Dist: pdfplumber>=0.11.8; extra == "dev"
Requires-Dist: reportlab>=4.4.9; extra == "dev"
Requires-Dist: py7zr>=1.1.2; extra == "dev"
Requires-Dist: pytest>=8.2; extra == "dev"
Requires-Dist: textual-dev>=1.8.0; extra == "dev"
Dynamic: license-file
